hack4u/__init__.py
hack4u/cursos.py
hack4u/utils.py
practica_1_hack4u-0.1.1.dist-info/METADATA
practica_1_hack4u-0.1.1.dist-info/WHEEL
practica_1_hack4u-0.1.1.dist-info/top_level.txt
practica_1_hack4u-0.1.1.dist-info/RECORD
