Metadata-Version: 2.1
Name: practica_1_hack4u
Version: 0.1.1
Summary: Una práctica de biblioteca donde consultar cursos de hack4u.
Home-page: https://hack4u.io
Author: Aport
